sdd/__init__.py
sdd/utils.py
sdd_utils-0.1.dist-info/LICENSE
sdd_utils-0.1.dist-info/METADATA
sdd_utils-0.1.dist-info/WHEEL
sdd_utils-0.1.dist-info/top_level.txt
sdd_utils-0.1.dist-info/RECORD
