Metadata-Version: 2.1
Name: sdd-utils
Version: 0.1
Summary: Small utilities for SDD project
Home-page: https://github.com/jjacostupa/sdd_utils
Author: Juan Acostupa
Author-email: jjacostupa@gmail.com
License: UNKNOWN
Platform: UNKNOWN
Classifier: Programming Language :: Python :: 3
Classifier: License :: OSI Approved :: MIT License
Classifier: Operating System :: OS Independent
Requires-Python: >=3.6
